bleach_allowlist/__init__.py
bleach_allowlist/bleach_allowlist.py
bleach_allowlist-1.0.3.dist-info/DESCRIPTION.rst
bleach_allowlist-1.0.3.dist-info/METADATA
bleach_allowlist-1.0.3.dist-info/RECORD
bleach_allowlist-1.0.3.dist-info/WHEEL
bleach_allowlist-1.0.3.dist-info/metadata.json
bleach_allowlist-1.0.3.dist-info/top_level.txt
