Metadata-Version: 1.1
Name: bleach-allowlist
Version: 1.0.3
Summary: Curated lists of tags and attributes for sanitizing html
Home-page: https://github.com/yourcelf/bleach-allowlist.git
Author: Charlie DeTar
Author-email: cfd@media.mit.edu
License: BSD License
Platform: UNKNOWN
Classifier: Environment :: Web Environment
Classifier: Intended Audience :: Developers
Classifier: License :: OSI Approved :: BSD License
Classifier: Operating System :: OS Independent
Classifier: Programming Language :: Python
Classifier: Topic :: Internet :: WWW/HTTP
Classifier: Topic :: Internet :: WWW/HTTP :: Dynamic Content
